satextrato/__init__.py
satextrato/base.py
satextrato/cancelamento.py
satextrato/config.py
satextrato/venda.py
satextrato-0.4.dist-info/LICENSE
satextrato-0.4.dist-info/METADATA
satextrato-0.4.dist-info/WHEEL
satextrato-0.4.dist-info/top_level.txt
satextrato-0.4.dist-info/RECORD
